crongateway/__init__.py
crongateway/client.py
crongateway-0.1.0.dist-info/METADATA
crongateway-0.1.0.dist-info/WHEEL
crongateway-0.1.0.dist-info/top_level.txt
crongateway-0.1.0.dist-info/RECORD
